mkdocs_solarized/__init__.py
mkdocs_solarized/cli.py
mkdocs_solarized/overrides/main.html
mkdocs_solarized/overrides/extra/refresh_on_toggle_dark_light.js
mkdocs_solarized/overrides/javascripts/gradient-animation.js
mkdocs_solarized/overrides/javascripts/mathjax.js
mkdocs_solarized/overrides/javascripts/tablesort.js
mkdocs_solarized/overrides/javascripts/typing-animation.js
mkdocs_solarized/overrides/stylesheets/extra.css
mkdocs_solarized/templates/mkdocs.yml
mkdocs_solarized-0.1.0.dist-info/METADATA
mkdocs_solarized-0.1.0.dist-info/WHEEL
mkdocs_solarized-0.1.0.dist-info/entry_points.txt
mkdocs_solarized-0.1.0.dist-info/top_level.txt
mkdocs_solarized-0.1.0.dist-info/RECORD
